memorywrapper/__init__.py
memorywrapper/make_slices.py
memorywrapper/memorywrapper.py
memorywrapper-0.0.1.dist-info/LICENSE
memorywrapper-0.0.1.dist-info/METADATA
memorywrapper-0.0.1.dist-info/WHEEL
memorywrapper-0.0.1.dist-info/top_level.txt
memorywrapper-0.0.1.dist-info/RECORD
