Metadata-Version: 2.1
Name: memorywrapper
Version: 0.0.1
Summary: Wrapping non-continuous buffers in a late-resolving slice'able buffer-compatible object
Author-email: Pierre LeMoine <pypi@luben.se>
License: MIT License
Project-URL: Homepage, https://github.com/DrInfiniteExplorer/py-memorywrapper
Project-URL: Repository, https://github.com/DrInfiniteExplorer/py-memorywrapper
Keywords: buffer,memoryview,memory,bytes
Classifier: Development Status :: 4 - Beta
Classifier: Programming Language :: Python :: 3
Classifier: License :: OSI Approved :: MIT License
Classifier: Operating System :: OS Independent
Requires-Python: >=3.12
License-File: LICENSE
